odoo10_addon_l10n_us_uom_profile-10.0.1.0.0-py2.7-nspkg.pth
odoo/addons/l10n_us_uom_profile/README.rst
odoo/addons/l10n_us_uom_profile/__init__.py
odoo/addons/l10n_us_uom_profile/__manifest__.py
odoo/addons/l10n_us_uom_profile/data/res_lang_data.xml
odoo10_addon_l10n_us_uom_profile-10.0.1.0.0.dist-info/DESCRIPTION.rst
odoo10_addon_l10n_us_uom_profile-10.0.1.0.0.dist-info/METADATA
odoo10_addon_l10n_us_uom_profile-10.0.1.0.0.dist-info/RECORD
odoo10_addon_l10n_us_uom_profile-10.0.1.0.0.dist-info/WHEEL
odoo10_addon_l10n_us_uom_profile-10.0.1.0.0.dist-info/metadata.json
odoo10_addon_l10n_us_uom_profile-10.0.1.0.0.dist-info/namespace_packages.txt
odoo10_addon_l10n_us_uom_profile-10.0.1.0.0.dist-info/top_level.txt
